instagramy/InstagramHashTag.py
instagramy/InstagramLocation.py
instagramy/InstagramPost.py
instagramy/InstagramUser.py
instagramy/__init__.py
instagramy/__main__.py
instagramy/core/__init__.py
instagramy/core/cache.py
instagramy/core/exceptions.py
instagramy/core/parser.py
instagramy/core/requests.py
instagramy/core/user_agent.py
instagramy/plugins/__init__.py
instagramy/plugins/analysis.py
instagramy/plugins/download.py
instagramy/plugins/manual_loading.py
test/__init__.py
test/test_instagramy.py
instagramy-4.4.dist-info/LICENSE.txt
instagramy-4.4.dist-info/METADATA
instagramy-4.4.dist-info/WHEEL
instagramy-4.4.dist-info/top_level.txt
instagramy-4.4.dist-info/RECORD
