Metadata-Version: 2.1
Name: instagramy
Version: 4.4
Summary: Python Package for Instagram User, Posts, Hashtags and Locations data
Home-page: https://github.com/yogeshwaran01/instagramy/
Author: Yogeshwaran R
Author-email: yogeshin247@gmail.com
License: MIT
Download-URL: https://github.com/yogeshwaran01/instagramy/archive/master.zip
Platform: UNKNOWN
Classifier: Programming Language :: Python :: 3
Classifier: License :: OSI Approved :: MIT License
Classifier: Operating System :: OS Independent
